mona_uds_client/__init__.py
mona_uds_client/mona_uds_client.py
mona_uds_client/mona_uds_client_test.py
mona_uds_client-0.0.8.dist-info/LICENSE
mona_uds_client-0.0.8.dist-info/METADATA
mona_uds_client-0.0.8.dist-info/WHEEL
mona_uds_client-0.0.8.dist-info/top_level.txt
mona_uds_client-0.0.8.dist-info/RECORD
