Metadata-Version: 2.1
Name: mona-uds-client
Version: 0.0.8
Summary: Client code for python Mona over Unix Domain Socket protocol
Home-page: https://github.com/monalabs/mona-uds-client
Author: MonaLabs
Author-email: nemo@monalabs.io
License: UNKNOWN
Download-URL: http://pypi.python.org/pypi/mona-uds-client/
Platform: UNKNOWN
Classifier: Programming Language :: Python :: 3
Classifier: License :: OSI Approved :: Apache Software License
Classifier: Operating System :: Unix
Requires-Python: >=3.7
Requires-Dist: msgpack (>=1.0.2)
